polymorphic_sqlalchemy/__init__.py
polymorphic_sqlalchemy/ext.py
polymorphic_sqlalchemy/misc.py
polymorphic_sqlalchemy-0.2.6.dist-info/DESCRIPTION.rst
polymorphic_sqlalchemy-0.2.6.dist-info/METADATA
polymorphic_sqlalchemy-0.2.6.dist-info/RECORD
polymorphic_sqlalchemy-0.2.6.dist-info/WHEEL
polymorphic_sqlalchemy-0.2.6.dist-info/metadata.json
polymorphic_sqlalchemy-0.2.6.dist-info/top_level.txt
