Metadata-Version: 2.0
Name: polymorphic-sqlalchemy
Version: 0.2.6
Summary: Polymorphic relations for SQLAlchemy
Home-page: https://github.com/wearefair/polymorphic_sqlalchemy
Author: Seperman
Author-email: sepd@fair.com
License: UNKNOWN
Download-URL: https://github.com/wearefair/polymorphic_sqlalchemy/tarball/master
Platform: UNKNOWN
Classifier: Intended Audience :: Developers
Classifier: Operating System :: OS Independent
Classifier: Topic :: Software Development
Classifier: Programming Language :: Python :: 3.5
Classifier: Programming Language :: Python :: 3.6
Classifier: Development Status :: 4 - Beta
Requires-Dist: SQLAlchemy
Requires-Dist: inflection
